lightbox/__init__.py
lightbox/middleware.py
lightbox/models.py
lightbox/tests.py
lightbox/urls.py
lightbox/views.py
lightbox/templates/lightbox/base.html
lightbox/templatetags/__init__.py
lightbox/templatetags/__init__.pyc
lightbox/templatetags/lightbox.py
lightbox/templatetags/lightbox.pyc
DjangoLightbox-0.2.2.dist-info/LICENSE.txt
DjangoLightbox-0.2.2.dist-info/METADATA
DjangoLightbox-0.2.2.dist-info/WHEEL
DjangoLightbox-0.2.2.dist-info/top_level.txt
DjangoLightbox-0.2.2.dist-info/RECORD
