Metadata-Version: 2.1
Name: DjangoLightbox
Version: 0.2.2
Summary: alternative for a full screen javascript lightbox for the django framework
Home-page: http://pypi.python.org/pypi/DjangoLightbox/
Author: Geert Dekkers
Author-email: geert@djangowebstudio.nl
License: LICENSE.txt
Keywords: lightbox images image presentation
Platform: UNKNOWN
Requires-Dist: Django (>=1.11)
Requires-Dist: sorl-thumbnail (>=12.5.0)
